{
  "parent": "minecraft:recipes/root",
  "criteria": {
    "has_block": {
      "trigger": "minecraft:inventory_changed",
      "conditions": {
        "items": [
          {
            "item": "minecraft:stick"
          }
        ]
      }
    }
  },
  "requirements": [
    ["has_block"]
  ],
  "rewards": {
    "recipes": [
      "sentimentality3:small_stick_bundle",
      "sentimentality3:small_stick_bundle_u",
      "sentimentality3:large_stick_bundle",
      "sentimentality3:large_stick_bundle_u"
    ]
  }
}